{
  "$schema": "https://developer.microsoft.com/json-schemas/fabric/item/report/definition/visualContainer/2.6.0/schema.json",
  "name": "4e318da4ff378f96acde",
  "position": {
    "x": 10,
    "y": 529,
    "z": 1,
    "height": 191,
    "width": 803,
    "tabOrder": 1
  },
  "visual": {
    "visualType": "clusteredColumnChart",
    "query": {
      "queryState": {
        "Category": {
          "projections": [
            {
              "field": {
                "Column": {
                  "Expression": {
                    "SourceRef": {
                      "Entity": "financials"
                    }
                  },
                  "Property": "Country"
                }
              },
              "queryRef": "financials.Country",
              "nativeQueryRef": "Country",
              "active": true
            }
          ]
        },
        "Y": {
          "projections": [
            {
              "field": {
                "Aggregation": {
                  "Expression": {
                    "Column": {
                      "Expression": {
                        "SourceRef": {
                          "Entity": "financials"
                        }
                      },
                      "Property": "COGS"
                    }
                  },
                  "Function": 0
                }
              },
              "queryRef": "Sum(financials.COGS)",
              "nativeQueryRef": "Sum of COGS"
            }
          ]
        }
      },
      "sortDefinition": {
        "sort": [
          {
            "field": {
              "Aggregation": {
                "Expression": {
                  "Column": {
                    "Expression": {
                      "SourceRef": {
                        "Entity": "financials"
                      }
                    },
                    "Property": "COGS"
                  }
                },
                "Function": 0
              }
            },
            "direction": "Descending"
          }
        ],
        "isDefaultSort": true
      }
    },
    "drillFilterOtherVisuals": true
  },
  "filterConfig": {
    "filters": [
      {
        "name": "97137a6e3e8c6976b7e7",
        "field": {
          "Aggregation": {
            "Expression": {
              "Column": {
                "Expression": {
                  "SourceRef": {
                    "Entity": "financials"
                  }
                },
                "Property": "COGS"
              }
            },
            "Function": 0
          }
        },
        "type": "Advanced"
      },
      {
        "name": "d29996ae7ac458a86d17",
        "field": {
          "Column": {
            "Expression": {
              "SourceRef": {
                "Entity": "financials"
              }
            },
            "Property": "Country"
          }
        },
        "type": "Categorical"
      }
    ]
  }
}